hindsight/__init__.py
hindsight/bokeh_init.py
hindsight/voila_init.py
hindsight/widgets.py
hindsight/static/__init__.py
hindsight/static/images/__init__.py
hindsight/static/images/loading.gif
hindsight/utils/__init__.py
hindsight/utils/bokeh.py
hindsight/utils/custom_css.py
hindsight/utils/voila.py
hindsight_storedot-1.0.6.dist-info/LICENSE
hindsight_storedot-1.0.6.dist-info/METADATA
hindsight_storedot-1.0.6.dist-info/WHEEL
hindsight_storedot-1.0.6.dist-info/top_level.txt
hindsight_storedot-1.0.6.dist-info/RECORD
