Metadata-Version: 2.1
Name: hindsight-storedot
Version: 1.0.6
Summary: jupyter utilities
Home-page: https://https://github.com/hindsight/banner
Author: GB
Author-email: gilb@store-dot.com
License: UNKNOWN
Project-URL: Bug Tracker, https://https://github.com/storedot/hindsight/issues
Platform: UNKNOWN
Classifier: Programming Language :: Python :: 3
Classifier: License :: OSI Approved :: MIT License
Classifier: Operating System :: OS Independent
Requires-Python: >=3.8
Requires-Dist: ipython
Requires-Dist: ipyvuetify
Requires-Dist: bokeh (>=2.4.2)
